checkpy/__init__.py
checkpy/__main__.py
checkpy/caches.py
checkpy/interactive.py
checkpy/tests.py
checkpy/assertlib/__init__.py
checkpy/assertlib/basic.py
checkpy/database/__init__.py
checkpy/database/database.py
checkpy/downloader/__init__.py
checkpy/downloader/downloader.py
checkpy/entities/__init__.py
checkpy/entities/exception.py
checkpy/entities/function.py
checkpy/entities/path.py
checkpy/lib/__init__.py
checkpy/lib/basic.py
checkpy/lib/declarative.py
checkpy/lib/explanation.py
checkpy/lib/io.py
checkpy/lib/monkeypatch.py
checkpy/lib/sandbox.py
checkpy/lib/static.py
checkpy/lib/type.py
checkpy/printer/__init__.py
checkpy/printer/printer.py
checkpy/tester/__init__.py
checkpy/tester/discovery.py
checkpy/tester/tester.py
checkpy-2.1.2.dist-info/licenses/LICENSE
checkpy-2.1.2.dist-info/METADATA
checkpy-2.1.2.dist-info/WHEEL
checkpy-2.1.2.dist-info/entry_points.txt
checkpy-2.1.2.dist-info/top_level.txt
checkpy-2.1.2.dist-info/RECORD
