Metadata-Version: 2.4
Name: checkPy
Version: 2.1.2
Summary: A simple python testing framework for educational purposes
Home-page: https://github.com/Jelleas/CheckPy
Author: Jelleas
Author-email: jelle.van.assema@gmail.com
License: MIT
Keywords: new unexperienced programmers automatic testing minor programming
Classifier: Development Status :: 4 - Beta
Classifier: Intended Audience :: Education
Classifier: Topic :: Education :: Testing
Classifier: License :: OSI Approved :: MIT License
Classifier: Programming Language :: Python :: 3
Classifier: Programming Language :: Python :: 3.7
License-File: LICENSE
Requires-Dist: requests
Requires-Dist: tinydb
Requires-Dist: dill
Requires-Dist: colorama
Requires-Dist: pytest
Requires-Dist: dessert
Requires-Dist: typeguard
Provides-Extra: dev
Provides-Extra: test
Dynamic: author
Dynamic: author-email
Dynamic: classifier
Dynamic: description
Dynamic: description-content-type
Dynamic: home-page
Dynamic: keywords
Dynamic: license
Dynamic: license-file
Dynamic: provides-extra
Dynamic: requires-dist
Dynamic: summary
